ffgrep.py
version.py
ffgrep-1.1.0.dist-info/licenses/LICENSE
ffgrep-1.1.0.dist-info/METADATA
ffgrep-1.1.0.dist-info/WHEEL
ffgrep-1.1.0.dist-info/entry_points.txt
ffgrep-1.1.0.dist-info/top_level.txt
ffgrep-1.1.0.dist-info/RECORD
